{
    "request": {
        "version": "0.0.11",
        "width": 1024,
        "height": 768,
        "music": "1.mp3",
        "rate": "1",
        "frames": [
            {
                "number": "1", 
                "time": 5, 
                "objects": [
                    {
                        "text": "春眠不觉晓", 
                        "x": 200,
                        "y": 200,
                        "size": 50,
                        "color": "0,255,0"
                    },
                    {
                        "text": "处处闻啼鸟", 
                        "x": 200,
                        "y": 300,
                        "size": 50,
                        "color": "0,255,0"
                    },
                    {
                        "text": "夜来风雨声", 
                        "x": 200,
                        "y": 400,
                        "size": 50,
                        "color": "0,255,0"
                    },
                    {
                        "text": "花落知多少", 
                        "x": 200,
                        "y": 500,
                        "size": 50,
                        "color": "0,255,0"
                    }
                ],
                "backgroundColor": "72,61,139"
            },
            {
                "number": "2", 
                "time": 5, 
                "objects": [
                    {
                        "text": "春眠不觉晓", 
                        "x": 200,
                        "y": 200,
                        "size": 80,
                        "color": "0,255,255"
                    },
                    {
                        "text": "处处闻啼鸟", 
                        "x": 200,
                        "y": 300,
                        "size": 50,
                        "color": "0,255,0"
                    },
                    {
                        "text": "夜来风雨声", 
                        "x": 200,
                        "y": 400,
                        "size": 50,
                        "color": "0,255,0"
                    },
                    {
                        "text": "花落知多少", 
                        "x": 200,
                        "y": 500,
                        "size": 50,
                        "color": "0,255,0"
                    }
                ],
                "backgroundColor": "72,61,139"
            },
            {
                "number": "3", 
                "time": 5, 
                "objects": [
                    {
                        "text": "春眠不觉晓", 
                        "x": 200,
                        "y": 200,
                        "size": 50,
                        "color": "0,255,0"
                    },
                    {
                        "text": "处处闻啼鸟", 
                        "x": 200,
                        "y": 300,
                        "size": 80,
                        "color": "0,255,255"
                    },
                    {
                        "text": "夜来风雨声", 
                        "x": 200,
                        "y": 400,
                        "size": 50,
                        "color": "0,255,0"
                    },
                    {
                        "text": "花落知多少", 
                        "x": 200,
                        "y": 500,
                        "size": 50,
                        "color": "0,255,0"
                    }
                ],
                "backgroundColor": "72,61,139"
            },
            {
                "number": "4", 
                "time": 5, 
                "objects": [
                    {
                        "text": "春眠不觉晓", 
                        "x": 200,
                        "y": 200,
                        "size": 50,
                        "color": "0,255,0"
                    },
                    {
                        "text": "处处闻啼鸟", 
                        "x": 200,
                        "y": 300,
                        "size": 50,
                        "color": "0,255,0"
                    },
                    {
                        "text": "夜来风雨声", 
                        "x": 200,
                        "y": 400,
                        "size": 80,
                        "color": "0,255,255"
                    },
                    {
                        "text": "花落知多少", 
                        "x": 200,
                        "y": 500,
                        "size": 50,
                        "color": "0,255,0"
                    }
                ],
                "backgroundColor": "72,61,139"
            },
            {
                "number": "5", 
                "time": 5, 
                "objects": [
                    {
                        "text": "春眠不觉晓", 
                        "x": 200,
                        "y": 200,
                        "size": 50,
                        "color": "0,255,0"
                    },
                    {
                        "text": "处处闻啼鸟", 
                        "x": 200,
                        "y": 300,
                        "size": 50,
                        "color": "0,255,0"
                    },
                    {
                        "text": "夜来风雨声", 
                        "x": 200,
                        "y": 400,
                        "size": 50,
                        "color": "0,255,0"
                    },
                    {
                        "text": "花落知多少", 
                        "x": 200,
                        "y": 500,
                        "size": 80,
                        "color": "0,255,255"
                    }
                ],
                "backgroundColor": "72,61,139"
            },
            {
                "number": "6", 
                "time": 5, 
                "objects": [
                    {
                        "text": "谢谢观看", 
                        "x": 200,
                        "y": 300,
                        "size": 100,
                        "color": "255,255,0"
                    },
                    {
                        "picture": "bb.gif",
                        "x": 200,
                        "y": 500,
                        "width":80,
                        "heigth":80
                    },
                    {
                        "picture": "https://gdb.voanews.com/6AD44B97-4251-4D10-B871-C134BBFB39FA_w256_r1.jpg",
                        "x": 300,
                        "y": 500,
                        "width":80,
                        "heigth":80
                    }
                ],
                "backgroundPicture": "bgpic.jpg"
            }
        ]
    }
}